<?xml version="1.0" encoding="utf-8"?>
<paths viewBox="-205.704 -201.424 1570.493 974.108">
	<path id="İslahiye_1360" stroke="#EFEFEF" stroke-width="0.25" d="M-9.181,227.502l185.833,154.315l95.215-42.682l23.641,55.159
		L193.071,541.384L82.753,574.217l-33.489,54.504H14.46l-219.981-114.915L-9.181,227.502z"/>
	<path id="Nurdağı_1363" stroke="#EFEFEF" stroke-width="0.25" d="M176.653,381.817l95.215-42.682l22.624,52.782l22.032-10.101
		l54.5-80.767l-48.593-154.974l-23.637-68.948l-19.7-22.981L206.86,35.758l-15.104,57.785L24.309,194.669l-33.489,32.833
		L176.653,381.817z"/>
	<path id="Şehitkamil_1366" stroke="#EFEFEF" stroke-width="0.25" d="M473.464,278.065l248.215,69.607l72.233,44.245l170.733,33.24
		l5.252-133.304l-49.907-64.352l34.147-91.274l-72.889-19.044l-82.74,42.026L755.827-11.52l3.94-24.956l-81.426,65.011
		l-129.363,0.656L414.364,166.432l-91.934-20.356l48.593,154.974L473.464,278.065z"/>
	<path id="Şahinbey_1365" stroke="#EFEFEF" stroke-width="0.25" d="M613.99,595.232l-200.941-59.756l-96.525-153.659l54.5-80.767
		l102.44-22.985l248.215,69.607l72.233,44.245l-31.519,36.195l-39.399,200.607l-51.219,112.944L613.99,595.232z"/>
	<path id="Oğuzeli_1364" stroke="#EFEFEF" stroke-width="0.25" d="M959.391,719.995l-87.993,52.533L722.994,628.721l39.399-200.607
		l31.519-36.195l170.733,33.24l1.312,118.855l86.682,101.126l21.666,74.855H959.391z"/>
	<path id="Karkamış_1361" stroke="#EFEFEF" stroke-width="0.25" d="M1052.639,645.14l145.118-166.138h93.903l17.074,142.822
		l-234.43,98.171L1052.639,645.14z"/>
	<path id="Nizip_1362" stroke="#EFEFEF" stroke-width="0.25" d="M954.139,136.228l-34.148,91.274l49.907,64.352l-5.252,133.304
		l1.312,118.855l86.682,101.126l145.118-166.138h93.903l-135.93-157.596l11.822-61.07l-38.744-163.507L954.139,136.228z"/>
	<path id="Yavuzeli_1367" stroke="#EFEFEF" stroke-width="0.25" d="M881.249,117.184l-82.74,42.026L755.827-11.52l3.94-24.956
		l45.967-12.474l290.241,26.922l73.548,20.355l-40.715,98.5l-174.671,39.4L881.249,117.184z"/>
	<path id="Araban_1359" stroke="#EFEFEF" stroke-width="0.25" d="M1364.55-120.527l-22.981,28.237l-83.396-12.478L1169.523-1.672
		l-68.941-19.079L805.734-48.95l95.871-130.019l150.374-22.326l93.903,53.188L1364.55-120.527z"/>
</paths>
